{
    "name":"svyUtils$webClient",
    "displayName":"svyUtils$webClient",
    "packageType": "Solution",
    "icon": "https://raw.githubusercontent.com/Servoy/servoy-extra-components/master/servoy.png",
    "description": "Set of utility methods specifically for the Servoy Web Client Also replaces (most) of the functionality of the WebClientUtils plugin",
    "wikiUrl": "https://github.com/Servoy/svyUtils/wiki",
    "sourceUrl" : "https://github.com/Servoy/svyUtils",
    "releases" : [
        {"version":"1.6.0","url":"https://github.com/Servoy/svyUtils/releases/download/v1.6.0/svyUtilsDocumentEditor.servoy", "servoy-version":"2021.06", "dependency":"smartDocumentEditor#>=1.0.0"}
     ]
}
